pymender/__init__.py
pymender/__main__.py
pymender/cli.py
pymender/commands/__init__.py
pymender/commands/fastapi_annotated.py
pymender/commands/tests/__init__.py
pymender/commands/tests/test_fastapi_annotated.py
pymender-0.2.0.dist-info/METADATA
pymender-0.2.0.dist-info/WHEEL
pymender-0.2.0.dist-info/entry_points.txt
pymender-0.2.0.dist-info/top_level.txt
pymender-0.2.0.dist-info/RECORD
