Metadata-Version: 2.1
Name: pymender
Version: 0.2.0
Summary: Mend your Python projects with reproducible refactors
Author-email: Daniel Hails <pymender@hails.info>
Project-URL: Homepage, https://github.com/DJRHails/pymender
Project-URL: Bug Tracker, https://github.com/DJRHails/pymender/issues
Requires-Python: >=3.10
Requires-Dist: libcst
Requires-Dist: gitignore-parser
